eo_bathymetry_functions/__init__.py
eo_bathymetry_functions/exceptions.py
eo_bathymetry_functions/export_rgb_tiles.py
eo_bathymetry_functions/export_tile_bathymetry.py
eo_bathymetry_functions/utils.py
eo_bathymetry_functions-0.8.0.dist-info/LICENSE
eo_bathymetry_functions-0.8.0.dist-info/METADATA
eo_bathymetry_functions-0.8.0.dist-info/WHEEL
eo_bathymetry_functions-0.8.0.dist-info/top_level.txt
eo_bathymetry_functions-0.8.0.dist-info/RECORD
