Metadata-Version: 2.1
Name: eo-bathymetry-functions
Version: 0.8.0
Summary: Functions work with EO bathymetry.
Home-page: https://github.com/openearth/eo-bathymetry-functions
Author: Jaap Langemeijer
Author-email: jaaplangemeijer@gmail.com
License: MIT
Classifier: License :: OSI Approved :: MIT License
Classifier: Programming Language :: Python
Classifier: Programming Language :: Python :: 3.8
License-File: LICENSE
Requires-Dist: eepackages (==0.17.0)
Requires-Dist: earthengine-api (==0.1.317)
Requires-Dist: geojson (>=2.5.0)
Requires-Dist: google-api-python-client (>=1.12.8)
Requires-Dist: python-dateutil (>=2.8.2)
